yt_transcript_dl/__init__.py
yt_transcript_dl/cli.py
yt_transcript_dl/config.py
yt_transcript_dl/downloader.py
yt_transcript_dl/formatters.py
yt_transcript_dl/sync_state.py
yt_transcript_dl/utils.py
ytdl_transcript-0.1.0.dist-info/METADATA
ytdl_transcript-0.1.0.dist-info/WHEEL
ytdl_transcript-0.1.0.dist-info/entry_points.txt
ytdl_transcript-0.1.0.dist-info/licenses/LICENSE
ytdl_transcript-0.1.0.dist-info/RECORD
