Metadata-Version: 2.4
Name: ytdl-transcript
Version: 0.1.0
Summary: Download YouTube video transcripts using yt-dlp
Project-URL: Homepage, https://github.com/rk/yt-transcript-dl
Project-URL: Repository, https://github.com/rk/yt-transcript-dl
Author: rk
License-Expression: MIT
License-File: LICENSE
Keywords: captions,subtitles,transcript,youtube,yt-dlp
Classifier: Development Status :: 4 - Beta
Classifier: Environment :: Console
Classifier: Intended Audience :: Developers
Classifier: Intended Audience :: End Users/Desktop
Classifier: License :: OSI Approved :: MIT License
Classifier: Operating System :: OS Independent
Classifier: Programming Language :: Python :: 3
Classifier: Programming Language :: Python :: 3.10
Classifier: Programming Language :: Python :: 3.11
Classifier: Programming Language :: Python :: 3.12
Classifier: Topic :: Multimedia :: Video
Classifier: Topic :: Text Processing
Requires-Python: >=3.10
Requires-Dist: click>=8.0
Requires-Dist: tomli>=2.0.0; python_version < '3.11'
Requires-Dist: yt-dlp>=2023.0.0
Provides-Extra: dev
Requires-Dist: pytest-cov>=4.0; extra == 'dev'
Requires-Dist: pytest>=7.0; extra == 'dev'
